sysinfo/__init__.py
sysinfo/sysinfo.py
sysinfobj-0.1.1.dist-info/LICENSE
sysinfobj-0.1.1.dist-info/METADATA
sysinfobj-0.1.1.dist-info/WHEEL
sysinfobj-0.1.1.dist-info/entry_points.txt
sysinfobj-0.1.1.dist-info/top_level.txt
sysinfobj-0.1.1.dist-info/RECORD
