Metadata-Version: 2.1
Name: sysinfobj
Version: 0.1.1
Summary: Linux system statistics
Home-page: https://github.com/bharathjakkani/sysinfo
Author: Bharath
Author-email: learnit.linux@gmail.com
Requires-Python: >=3.7
License-File: LICENSE
Requires-Dist: psutil
